funcsfrequse/__init__.py
funcsfrequse/setup.py
funcsfrequse/odps/__init__.py
funcsfrequse/odps/funcs.py
funcsfrequse/odps_passvar/__init__.py
funcsfrequse/odps_passvar/funcs.py
funcsfrequse/selfdev/__init__.py
funcsfrequse/selfdev/funcs.py
funcsfrequse-0.0.2.dist-info/METADATA
funcsfrequse-0.0.2.dist-info/WHEEL
funcsfrequse-0.0.2.dist-info/top_level.txt
funcsfrequse-0.0.2.dist-info/RECORD
